{"nodes": [{"id": "lib_google_translate_ts", "label": "google-translate.ts", "file_type": "code", "source_file": "lib/google-translate.ts", "source_location": "L1"}, {"id": "google_translate_preparefortranslation", "label": "prepareForTranslation()", "file_type": "code", "source_file": "lib/google-translate.ts", "source_location": "L25"}, {"id": "google_translate_restorefromtranslation", "label": "restoreFromTranslation()", "file_type": "code", "source_file": "lib/google-translate.ts", "source_location": "L37"}, {"id": "google_translate_decodehtmlentities", "label": "decodeHtmlEntities()", "file_type": "code", "source_file": "lib/google-translate.ts", "source_location": "L46"}, {"id": "google_translate_translatetext", "label": "translateText()", "file_type": "code", "source_file": "lib/google-translate.ts", "source_location": "L65"}, {"id": "google_translate_translatebatch", "label": "translateBatch()", "file_type": "code", "source_file": "lib/google-translate.ts", "source_location": "L114"}, {"id": "google_translate_getsupportedlanguages", "label": "getSupportedLanguages()", "file_type": "code", "source_file": "lib/google-translate.ts", "source_location": "L180"}], "edges": [{"source": "lib_google_translate_ts", "target": "google_translate_preparefortranslation", "relation": "contains", "confidence": "EXTRACTED", "source_file": "lib/google-translate.ts", "source_location": "L25", "weight": 1.0}, {"source": "lib_google_translate_ts", "target": "google_translate_restorefromtranslation", "relation": "contains", "confidence": "EXTRACTED", "source_file": "lib/google-translate.ts", "source_location": "L37", "weight": 1.0}, {"source": "lib_google_translate_ts", "target": "google_translate_decodehtmlentities", "relation": "contains", "confidence": "EXTRACTED", "source_file": "lib/google-translate.ts", "source_location": "L46", "weight": 1.0}, {"source": "lib_google_translate_ts", "target": "google_translate_translatetext", "relation": "contains", "confidence": "EXTRACTED", "source_file": "lib/google-translate.ts", "source_location": "L65", "weight": 1.0}, {"source": "lib_google_translate_ts", "target": "google_translate_translatebatch", "relation": "contains", "confidence": "EXTRACTED", "source_file": "lib/google-translate.ts", "source_location": "L114", "weight": 1.0}, {"source": "lib_google_translate_ts", "target": "google_translate_getsupportedlanguages", "relation": "contains", "confidence": "EXTRACTED", "source_file": "lib/google-translate.ts", "source_location": "L180", "weight": 1.0}, {"source": "google_translate_translatetext", "target": "google_translate_translatebatch", "relation": "calls", "confidence": "EXTRACTED", "source_file": "lib/google-translate.ts", "source_location": "L78", "weight": 1.0}, {"source": "google_translate_translatetext", "target": "google_translate_preparefortranslation", "relation": "calls", "confidence": "EXTRACTED", "source_file": "lib/google-translate.ts", "source_location": "L82", "weight": 1.0}, {"source": "google_translate_translatetext", "target": "google_translate_decodehtmlentities", "relation": "calls", "confidence": "EXTRACTED", "source_file": "lib/google-translate.ts", "source_location": "L102", "weight": 1.0}, {"source": "google_translate_translatetext", "target": "google_translate_restorefromtranslation", "relation": "calls", "confidence": "EXTRACTED", "source_file": "lib/google-translate.ts", "source_location": "L102", "weight": 1.0}]}