{"nodes": [{"id": "manzhil_logo_brand", "label": "Manzhil Brand Logo", "file_type": "image", "source_file": "public/manzhil_logo.png", "source_location": null, "source_url": null, "captured_at": null, "author": null, "contributor": null}, {"id": "manzhil_logo_visual_style", "label": "Teal/Dark Green Color Scheme", "file_type": "image", "source_file": "public/manzhil_logo.png", "source_location": null, "source_url": null, "captured_at": null, "author": null, "contributor": null}, {"id": "manzhil_logo_symbolism_building", "label": "Multi-Story Building / Apartment Complex Symbol", "file_type": "image", "source_file": "public/manzhil_logo.png", "source_location": null, "source_url": null, "captured_at": null, "author": null, "contributor": null}, {"id": "manzhil_logo_symbolism_chat", "label": "Speech Bubble / Chat Balloon Symbol", "file_type": "image", "source_file": "public/manzhil_logo.png", "source_location": null, "source_url": null, "captured_at": null, "author": null, "contributor": null}, {"id": "manzhil_logo_typography", "label": "Flat Geometric Sans-Serif Iconographic Style", "file_type": "image", "source_file": "public/manzhil_logo.png", "source_location": null, "source_url": null, "captured_at": null, "author": null, "contributor": null}], "edges": [{"source": "manzhil_logo_brand", "target": "manzhil_logo_visual_style", "relation": "conceptually_related_to", "confidence": "EXTRACTED", "confidence_score": 1.0, "source_file": "public/manzhil_logo.png", "source_location": null, "weight": 1.0}, {"source": "manzhil_logo_brand", "target": "manzhil_logo_symbolism_building", "relation": "conceptually_related_to", "confidence": "EXTRACTED", "confidence_score": 1.0, "source_file": "public/manzhil_logo.png", "source_location": null, "weight": 1.0}, {"source": "manzhil_logo_brand", "target": "manzhil_logo_symbolism_chat", "relation": "conceptually_related_to", "confidence": "EXTRACTED", "confidence_score": 1.0, "source_file": "public/manzhil_logo.png", "source_location": null, "weight": 1.0}, {"source": "manzhil_logo_brand", "target": "manzhil_logo_typography", "relation": "conceptually_related_to", "confidence": "EXTRACTED", "confidence_score": 1.0, "source_file": "public/manzhil_logo.png", "source_location": null, "weight": 1.0}, {"source": "manzhil_logo_symbolism_building", "target": "manzhil_app_bms", "relation": "rationale_for", "confidence": "INFERRED", "confidence_score": 0.9, "source_file": "public/manzhil_logo.png", "source_location": null, "weight": 0.9}, {"source": "manzhil_logo_symbolism_chat", "target": "manzhil_app_bms", "relation": "rationale_for", "confidence": "INFERRED", "confidence_score": 0.85, "source_file": "public/manzhil_logo.png", "source_location": null, "weight": 0.85}, {"source": "manzhil_logo_brand", "target": "manzhil_app_bms", "relation": "conceptually_related_to", "confidence": "INFERRED", "confidence_score": 0.9, "source_file": "public/manzhil_logo.png", "source_location": null, "weight": 0.9}], "hyperedges": []}