{"nodes": [{"id": "lib_twilio_send_ts", "label": "send.ts", "file_type": "code", "source_file": "lib/twilio/send.ts", "source_location": "L1"}, {"id": "send_sendmessage", "label": "sendMessage()", "file_type": "code", "source_file": "lib/twilio/send.ts", "source_location": "L20"}, {"id": "send_sendtemplate", "label": "sendTemplate()", "file_type": "code", "source_file": "lib/twilio/send.ts", "source_location": "L52"}, {"id": "send_sendwithfallback", "label": "sendWithFallback()", "file_type": "code", "source_file": "lib/twilio/send.ts", "source_location": "L96"}], "edges": [{"source": "lib_twilio_send_ts", "target": "lib_twilio_client", "relation": "imports_from", "confidence": "EXTRACTED", "source_file": "lib/twilio/send.ts", "source_location": "L7", "weight": 1.0}, {"source": "lib_twilio_send_ts", "target": "lib_twilio_session_tracker", "relation": "imports_from", "confidence": "EXTRACTED", "source_file": "lib/twilio/send.ts", "source_location": "L8", "weight": 1.0}, {"source": "lib_twilio_send_ts", "target": "lib_twilio_types", "relation": "imports_from", "confidence": "EXTRACTED", "source_file": "lib/twilio/send.ts", "source_location": "L9", "weight": 1.0}, {"source": "lib_twilio_send_ts", "target": "logger", "relation": "imports_from", "confidence": "EXTRACTED", "source_file": "lib/twilio/send.ts", "source_location": "L10", "weight": 1.0}, {"source": "lib_twilio_send_ts", "target": "send_sendmessage", "relation": "contains", "confidence": "EXTRACTED", "source_file": "lib/twilio/send.ts", "source_location": "L20", "weight": 1.0}, {"source": "lib_twilio_send_ts", "target": "send_sendtemplate", "relation": "contains", "confidence": "EXTRACTED", "source_file": "lib/twilio/send.ts", "source_location": "L52", "weight": 1.0}, {"source": "lib_twilio_send_ts", "target": "send_sendwithfallback", "relation": "contains", "confidence": "EXTRACTED", "source_file": "lib/twilio/send.ts", "source_location": "L96", "weight": 1.0}, {"source": "send_sendwithfallback", "target": "send_sendmessage", "relation": "calls", "confidence": "EXTRACTED", "source_file": "lib/twilio/send.ts", "source_location": "L108", "weight": 1.0}, {"source": "send_sendwithfallback", "target": "send_sendtemplate", "relation": "calls", "confidence": "EXTRACTED", "source_file": "lib/twilio/send.ts", "source_location": "L114", "weight": 1.0}]}